scrapy_redis_sentinel/__init__.py
scrapy_redis_sentinel/bloomfilter.py
scrapy_redis_sentinel/connection.py
scrapy_redis_sentinel/defaults.py
scrapy_redis_sentinel/dupefilter.py
scrapy_redis_sentinel/picklecompat.py
scrapy_redis_sentinel/pipelines.py
scrapy_redis_sentinel/queue.py
scrapy_redis_sentinel/scheduler.py
scrapy_redis_sentinel/spiders.py
scrapy_redis_sentinel/stats.py
scrapy_redis_sentinel/utils.py
scrapy_redis_sentinel-0.7.2.dist-info/LICENSE
scrapy_redis_sentinel-0.7.2.dist-info/METADATA
scrapy_redis_sentinel-0.7.2.dist-info/WHEEL
scrapy_redis_sentinel-0.7.2.dist-info/top_level.txt
scrapy_redis_sentinel-0.7.2.dist-info/RECORD
