Metadata-Version: 2.1
Name: scrapy-redis-sentinel
Version: 0.7.2
Summary: Redis Cluster for Scrapy.
Home-page: https://github.com/crawlmap/scrapy-redis-sentinel.git
Author: Shi Tao
Author-email: shitao0418@gmail.com
License: MIT
Project-URL: Documentation, https://crawlaio.com/scrapy-redis-sentinel/
Keywords: scrapy-redis,scrapy-redis-sentinel,scrapy-redis-cluster
Platform: UNKNOWN
Classifier: License :: OSI Approved :: MIT License
Classifier: Programming Language :: Python :: 3.6
Classifier: Programming Language :: Python :: 3.7
Classifier: Programming Language :: Python :: 3.8
Classifier: Programming Language :: Python :: 3.9
License-File: LICENSE
Requires-Dist: redis (==3.5.3)
Requires-Dist: redis-py-cluster (==2.1.3)
Requires-Dist: Scrapy
